[
    {
        "主題":"學習歷程",
        "內容":"&emsp;&emsp;巴拉拉巴拉巴拉拉巴拉巴拉拉巴拉巴拉拉巴拉巴拉拉巴拉巴拉拉巴拉巴拉拉巴拉巴你學姊好可愛拉拉巴拉巴拉拉巴拉巴拉拉巴拉巴拉拉巴拉巴拉拉巴拉巴拉拉巴拉巴拉拉巴拉巴拉拉巴拉巴拉拉巴拉",
        "圖片":"imgs/首圖/中興/中興圖書館.jpg"
    },
    {
        "主題":"研究/實習",
        "內容":"&emsp;&emsp;巴拉拉巴拉巴拉拉巴拉巴拉拉巴拉巴拉拉巴拉巴拉拉巴拉巴拉拉巴拉巴拉拉巴拉巴你學姊好可愛拉拉巴拉巴拉拉巴拉巴拉拉巴拉巴拉拉巴拉巴拉拉巴拉巴拉拉巴拉巴拉拉巴拉巴拉拉巴拉巴拉拉巴拉",
        "圖片":"imgs/首圖/中興/中興_1.jpg"
    },
    {
        "主題":"就讀動機",
        "內容":"&emsp;&emsp;巴拉拉巴拉巴拉拉巴拉巴拉拉巴拉巴拉拉巴拉巴拉拉巴拉巴拉拉巴拉巴拉拉巴拉巴你學姊好可愛拉拉巴拉巴拉拉巴拉巴拉拉巴拉巴拉拉巴拉巴拉拉巴拉巴拉拉巴拉巴拉拉巴拉巴拉拉巴拉巴拉拉巴拉",
        "圖片":"imgs/首圖/中興/中興湖.jpg"
    }
]